Metadata-Version: 1.0
Name: nandi
Version: 0.202
Summary: Simple data get utilities to pull stock data from web
Home-page: http://github.com/nandi-git/nandi-package
Author: Satish Nandi
Author-email: satish@nandi.net
License: MIT
Platform: UNKNOWN
